backtest/__init__.py
backtest/backtest.py
backtest/display_backtest.py
backtest/strategy.py
backtesting_package-1.2.dist-info/LICENSE
backtesting_package-1.2.dist-info/METADATA
backtesting_package-1.2.dist-info/WHEEL
backtesting_package-1.2.dist-info/top_level.txt
backtesting_package-1.2.dist-info/RECORD
