Metadata-Version: 2.1
Name: backtesting-package
Version: 1.2
Summary: Framework for backtesting algorithmic trading strategies
Home-page: https://github.com/leopoldcosson/backtesting-package
Author: Léopold Cosson
Author-email: leopoldcosson@gmail.com
License: MIT License with Restrictions
Platform: UNKNOWN
Classifier: Programming Language :: Python :: 3
Classifier: License :: OSI Approved :: MIT License
Classifier: Operating System :: OS Independent
Requires-Python: >=3.6
Requires-Dist: pandas
Requires-Dist: tqdm
Requires-Dist: plotly
Requires-Dist: numpy
Requires-Dist: yfinance
